{
  "submission_id": "95b21ece0000-4000-8000-c510193139d5",
  "created_at": "2026-06-18T06:47:25.787Z",
  "difficulty": "Easy",
  "db_type": "Snowflake",
  "domain": "Retail",
  "business_question": "What is the total inventory on hand per warehouse as of 2000?",
  "business_context": "Supply chain planners need a snapshot of total inventory on hand per warehouse for 2000 to identify stocking imbalances.",
  "metrics": {
    "kpis": [
      "Total Inventory On Hand by Warehouse"
    ],
    "aggregation_logic": {
      "Total Inventory On Hand by Warehouse": "SUM(inv_quantity_on_hand) grouped by warehouse for year 2000"
    }
  },
  "chain_of_thought": [
    "Use inventory as the fact table which holds periodic on-hand snapshots.",
    "Join to date_dim and filter WHERE d_year = 2000 to scope to that period.",
    "Join to warehouse dimension for human-readable warehouse name and state.",
    "Aggregate inv_quantity_on_hand with SUM per warehouse.",
    "Order by total on hand descending to identify the most stocked facilities."
  ],
  "schema_tables": {
    "fact_tables": [
      "inventory"
    ],
    "dimension_tables": [
      "warehouse",
      "date_dim"
    ]
  },
  "data_model_layers": {
    "hierarchies": "Date > Year, Warehouse",
    "aggregations": "",
    "snapshots": "Inventory on-hand"
  },
  "sql_answer": "SELECT\n  w.w_warehouse_name AS warehouse_name,\n  w.w_state AS warehouse_state,\n  SUM(inv.inv_quantity_on_hand) AS total_on_hand\nFROM inventory inv\nJOIN date_dim d ON inv.inv_date_sk = d.d_date_sk\nJOIN warehouse w ON inv.inv_warehouse_sk = w.w_warehouse_sk\nWHERE d.d_year = 2000\nGROUP BY w.w_warehouse_name, w.w_state\nORDER BY total_on_hand DESC;",
  "status": "pending"
}
